pyaesni.cp39-win_amd64.pyd
pyaesni-0.16.dist-info/LICENSE
pyaesni-0.16.dist-info/METADATA
pyaesni-0.16.dist-info/WHEEL
pyaesni-0.16.dist-info/top_level.txt
pyaesni-0.16.dist-info/RECORD
