Metadata-Version: 2.1
Name: pyaesni
Version: 0.16
Summary: python bindings for aes ni
Home-page: https://github.com/painor/pyaesni
Author: Painor
Author-email: pi.oussama@gmail.com
License: MIT License
Keywords: aesni encryption crypto decryption ige
Platform: UNKNOWN
Classifier: Development Status :: 4 - Beta
Classifier: License :: OSI Approved :: MIT License
Classifier: Programming Language :: Python
Classifier: Programming Language :: Python :: 3
Classifier: Programming Language :: Python :: 3.6
Classifier: Programming Language :: Python :: 3.7
Classifier: Programming Language :: Python :: 3.8
Classifier: Programming Language :: Python :: 3.9
Requires-Python: >=3.6
